<?xml version="1.0" encoding="utf-8" ?>
<dwsync>
<file name="fileSequence0.ts" server="headless.worldsecuresystems.com" local="130078807370000000" remote="130078807370000000" Dst="0" />
<file name="fileSequence1.ts" server="headless.worldsecuresystems.com" local="130078807440000000" remote="130078807440000000" Dst="0" />
<file name="fileSequence2.ts" server="headless.worldsecuresystems.com" local="130078807550000000" remote="130078807550000000" Dst="0" />
<file name="fileSequence3.ts" server="headless.worldsecuresystems.com" local="130078807670000000" remote="130078807670000000" Dst="0" />
<file name="fileSequence4.ts" server="headless.worldsecuresystems.com" local="130078807790000000" remote="130078807790000000" Dst="0" />
<file name="fileSequence5.ts" server="headless.worldsecuresystems.com" local="130078807920000000" remote="130078807920000000" Dst="0" />
<file name="fileSequence6.ts" server="headless.worldsecuresystems.com" local="130078808070000000" remote="130078808070000000" Dst="0" />
<file name="fileSequence7.ts" server="headless.worldsecuresystems.com" local="130078808220000000" remote="130078808220000000" Dst="0" />
<file name="fileSequence8.ts" server="headless.worldsecuresystems.com" local="130078808330000000" remote="130078808330000000" Dst="0" />
<file name="prog_index.m3u8" server="headless.worldsecuresystems.com" local="130078808340000000" remote="130078808340000000" Dst="0" />
<file name="prog_info.plist" server="headless.worldsecuresystems.com" local="130078808350000000" remote="130078808350000000" Dst="0" />
</dwsync>