<?xml version="1.0" encoding="utf-8" ?>
<dwsync>
<file name="fileSequence0.ts" server="headless.worldsecuresystems.com" local="130088568270000000" remote="130088568270000000" Dst="0" />
<file name="fileSequence1.ts" server="headless.worldsecuresystems.com" local="130088568310000000" remote="130088568310000000" Dst="0" />
<file name="fileSequence10.ts" server="headless.worldsecuresystems.com" local="130088568350000000" remote="130088568350000000" Dst="0" />
<file name="fileSequence11.ts" server="headless.worldsecuresystems.com" local="130088568400000000" remote="130088568400000000" Dst="0" />
<file name="fileSequence12.ts" server="headless.worldsecuresystems.com" local="130088568450000000" remote="130088568450000000" Dst="0" />
<file name="fileSequence13.ts" server="headless.worldsecuresystems.com" local="130088568490000000" remote="130088568490000000" Dst="0" />
<file name="fileSequence14.ts" server="headless.worldsecuresystems.com" local="130088568540000000" remote="130088568540000000" Dst="0" />
<file name="fileSequence15.ts" server="headless.worldsecuresystems.com" local="130088568580000000" remote="130088568580000000" Dst="0" />
<file name="fileSequence16.ts" server="headless.worldsecuresystems.com" local="130088568620000000" remote="130088568620000000" Dst="0" />
<file name="fileSequence17.ts" server="headless.worldsecuresystems.com" local="130088568660000000" remote="130088568660000000" Dst="0" />
<file name="fileSequence18.ts" server="headless.worldsecuresystems.com" local="130088568700000000" remote="130088568700000000" Dst="0" />
<file name="fileSequence19.ts" server="headless.worldsecuresystems.com" local="130088568730000000" remote="130088568730000000" Dst="0" />
<file name="fileSequence2.ts" server="headless.worldsecuresystems.com" local="130088568750000000" remote="130088568750000000" Dst="0" />
<file name="fileSequence20.ts" server="headless.worldsecuresystems.com" local="130088568790000000" remote="130088568790000000" Dst="0" />
<file name="fileSequence21.ts" server="headless.worldsecuresystems.com" local="130088568840000000" remote="130088568840000000" Dst="0" />
<file name="fileSequence22.ts" server="headless.worldsecuresystems.com" local="130088568870000000" remote="130088568870000000" Dst="0" />
<file name="fileSequence23.ts" server="headless.worldsecuresystems.com" local="130088568910000000" remote="130088568910000000" Dst="0" />
<file name="fileSequence24.ts" server="headless.worldsecuresystems.com" local="130088568950000000" remote="130088568950000000" Dst="0" />
<file name="fileSequence25.ts" server="headless.worldsecuresystems.com" local="130088568990000000" remote="130088568990000000" Dst="0" />
<file name="fileSequence26.ts" server="headless.worldsecuresystems.com" local="130088569030000000" remote="130088569030000000" Dst="0" />
<file name="fileSequence27.ts" server="headless.worldsecuresystems.com" local="130088569070000000" remote="130088569070000000" Dst="0" />
<file name="fileSequence28.ts" server="headless.worldsecuresystems.com" local="130088569110000000" remote="130088569110000000" Dst="0" />
<file name="fileSequence29.ts" server="headless.worldsecuresystems.com" local="130088569150000000" remote="130088569150000000" Dst="0" />
<file name="fileSequence3.ts" server="headless.worldsecuresystems.com" local="130088569180000000" remote="130088569180000000" Dst="0" />
<file name="fileSequence30.ts" server="headless.worldsecuresystems.com" local="130088569210000000" remote="130088569210000000" Dst="0" />
<file name="fileSequence31.ts" server="headless.worldsecuresystems.com" local="130088569250000000" remote="130088569250000000" Dst="0" />
<file name="fileSequence32.ts" server="headless.worldsecuresystems.com" local="130088569290000000" remote="130088569290000000" Dst="0" />
<file name="fileSequence33.ts" server="headless.worldsecuresystems.com" local="130088569330000000" remote="130088569330000000" Dst="0" />
<file name="fileSequence34.ts" server="headless.worldsecuresystems.com" local="130088569370000000" remote="130088569370000000" Dst="0" />
<file name="fileSequence35.ts" server="headless.worldsecuresystems.com" local="130088569410000000" remote="130088569410000000" Dst="0" />
<file name="fileSequence36.ts" server="headless.worldsecuresystems.com" local="130088569450000000" remote="130088569450000000" Dst="0" />
<file name="fileSequence37.ts" server="headless.worldsecuresystems.com" local="130088569490000000" remote="130088569490000000" Dst="0" />
<file name="fileSequence38.ts" server="headless.worldsecuresystems.com" local="130088569520000000" remote="130088569520000000" Dst="0" />
<file name="fileSequence39.ts" server="headless.worldsecuresystems.com" local="130088569570000000" remote="130088569570000000" Dst="0" />
<file name="fileSequence4.ts" server="headless.worldsecuresystems.com" local="130088569590000000" remote="130088569590000000" Dst="0" />
<file name="fileSequence40.ts" server="headless.worldsecuresystems.com" local="130088569630000000" remote="130088569630000000" Dst="0" />
<file name="fileSequence41.ts" server="headless.worldsecuresystems.com" local="130088569670000000" remote="130088569670000000" Dst="0" />
<file name="fileSequence42.ts" server="headless.worldsecuresystems.com" local="130088569710000000" remote="130088569710000000" Dst="0" />
<file name="fileSequence43.ts" server="headless.worldsecuresystems.com" local="130088569750000000" remote="130088569750000000" Dst="0" />
<file name="fileSequence44.ts" server="headless.worldsecuresystems.com" local="130088569790000000" remote="130088569790000000" Dst="0" />
<file name="fileSequence45.ts" server="headless.worldsecuresystems.com" local="130088569830000000" remote="130088569830000000" Dst="0" />
<file name="fileSequence46.ts" server="headless.worldsecuresystems.com" local="130088569870000000" remote="130088569870000000" Dst="0" />
<file name="fileSequence47.ts" server="headless.worldsecuresystems.com" local="130088569900000000" remote="130088569900000000" Dst="0" />
<file name="fileSequence48.ts" server="headless.worldsecuresystems.com" local="130088569950000000" remote="130088569950000000" Dst="0" />
<file name="fileSequence49.ts" server="headless.worldsecuresystems.com" local="130088569990000000" remote="130088569990000000" Dst="0" />
<file name="fileSequence5.ts" server="headless.worldsecuresystems.com" local="130088570020000000" remote="130088570020000000" Dst="0" />
<file name="fileSequence50.ts" server="headless.worldsecuresystems.com" local="130088570060000000" remote="130088570060000000" Dst="0" />
<file name="fileSequence51.ts" server="headless.worldsecuresystems.com" local="130088570100000000" remote="130088570100000000" Dst="0" />
<file name="fileSequence52.ts" server="headless.worldsecuresystems.com" local="130088570140000000" remote="130088570140000000" Dst="0" />
<file name="fileSequence53.ts" server="headless.worldsecuresystems.com" local="130088570180000000" remote="130088570180000000" Dst="0" />
<file name="fileSequence54.ts" server="headless.worldsecuresystems.com" local="130088570220000000" remote="130088570220000000" Dst="0" />
<file name="fileSequence55.ts" server="headless.worldsecuresystems.com" local="130088570280000000" remote="130088570280000000" Dst="0" />
<file name="fileSequence56.ts" server="headless.worldsecuresystems.com" local="130088570310000000" remote="130088570310000000" Dst="0" />
<file name="fileSequence57.ts" server="headless.worldsecuresystems.com" local="130088570350000000" remote="130088570350000000" Dst="0" />
<file name="fileSequence58.ts" server="headless.worldsecuresystems.com" local="130088570390000000" remote="130088570390000000" Dst="0" />
<file name="fileSequence59.ts" server="headless.worldsecuresystems.com" local="130088570440000000" remote="130088570440000000" Dst="0" />
<file name="fileSequence6.ts" server="headless.worldsecuresystems.com" local="130088570470000000" remote="130088570470000000" Dst="0" />
<file name="fileSequence60.ts" server="headless.worldsecuresystems.com" local="130088570510000000" remote="130088570510000000" Dst="0" />
<file name="fileSequence61.ts" server="headless.worldsecuresystems.com" local="130088570540000000" remote="130088570540000000" Dst="0" />
<file name="fileSequence62.ts" server="headless.worldsecuresystems.com" local="130088570580000000" remote="130088570580000000" Dst="0" />
<file name="fileSequence63.ts" server="headless.worldsecuresystems.com" local="130088570620000000" remote="130088570620000000" Dst="0" />
<file name="fileSequence64.ts" server="headless.worldsecuresystems.com" local="130088570660000000" remote="130088570660000000" Dst="0" />
<file name="fileSequence65.ts" server="headless.worldsecuresystems.com" local="130088570700000000" remote="130088570700000000" Dst="0" />
<file name="fileSequence66.ts" server="headless.worldsecuresystems.com" local="130088570730000000" remote="130088570730000000" Dst="0" />
<file name="fileSequence67.ts" server="headless.worldsecuresystems.com" local="130088570770000000" remote="130088570770000000" Dst="0" />
<file name="fileSequence68.ts" server="headless.worldsecuresystems.com" local="130088570820000000" remote="130088570820000000" Dst="0" />
<file name="fileSequence69.ts" server="headless.worldsecuresystems.com" local="130088570860000000" remote="130088570860000000" Dst="0" />
<file name="fileSequence7.ts" server="headless.worldsecuresystems.com" local="130088570900000000" remote="130088570900000000" Dst="0" />
<file name="fileSequence70.ts" server="headless.worldsecuresystems.com" local="130088570930000000" remote="130088570930000000" Dst="0" />
<file name="fileSequence71.ts" server="headless.worldsecuresystems.com" local="130088570970000000" remote="130088570970000000" Dst="0" />
<file name="fileSequence72.ts" server="headless.worldsecuresystems.com" local="130088571020000000" remote="130088571020000000" Dst="0" />
<file name="fileSequence73.ts" server="headless.worldsecuresystems.com" local="130088571070000000" remote="130088571070000000" Dst="0" />
<file name="fileSequence74.ts" server="headless.worldsecuresystems.com" local="130088571090000000" remote="130088571090000000" Dst="0" />
<file name="fileSequence75.ts" server="headless.worldsecuresystems.com" local="130088571110000000" remote="130088571110000000" Dst="0" />
<file name="fileSequence76.ts" server="headless.worldsecuresystems.com" local="130088571130000000" remote="130088571130000000" Dst="0" />
<file name="fileSequence77.ts" server="headless.worldsecuresystems.com" local="130088571130000000" remote="130088571130000000" Dst="0" />
<file name="fileSequence8.ts" server="headless.worldsecuresystems.com" local="130088571170000000" remote="130088571170000000" Dst="0" />
<file name="fileSequence9.ts" server="headless.worldsecuresystems.com" local="130088571220000000" remote="130088571220000000" Dst="0" />
<file name="prog_index.m3u8" server="headless.worldsecuresystems.com" local="130088571220000000" remote="130088571220000000" Dst="0" />
<file name="prog_info.plist" server="headless.worldsecuresystems.com" local="130088571230000000" remote="130088571230000000" Dst="0" />
</dwsync>