<?xml version="1.0" encoding="utf-8" ?>
<dwsync>
<file name="fileSequence0.ts" server="headless.worldsecuresystems.com" local="130079158710000000" remote="130079158710000000" Dst="0" />
<file name="fileSequence1.ts" server="headless.worldsecuresystems.com" local="130079158740000000" remote="130079158740000000" Dst="0" />
<file name="fileSequence10.ts" server="headless.worldsecuresystems.com" local="130079158780000000" remote="130079158780000000" Dst="0" />
<file name="fileSequence11.ts" server="headless.worldsecuresystems.com" local="130079158820000000" remote="130079158820000000" Dst="0" />
<file name="fileSequence12.ts" server="headless.worldsecuresystems.com" local="130079158860000000" remote="130079158860000000" Dst="0" />
<file name="fileSequence13.ts" server="headless.worldsecuresystems.com" local="130079158910000000" remote="130079158910000000" Dst="0" />
<file name="fileSequence14.ts" server="headless.worldsecuresystems.com" local="130079158950000000" remote="130079158950000000" Dst="0" />
<file name="fileSequence15.ts" server="headless.worldsecuresystems.com" local="130079158990000000" remote="130079158990000000" Dst="0" />
<file name="fileSequence16.ts" server="headless.worldsecuresystems.com" local="130079159040000000" remote="130079159040000000" Dst="0" />
<file name="fileSequence17.ts" server="headless.worldsecuresystems.com" local="130079159080000000" remote="130079159080000000" Dst="0" />
<file name="fileSequence18.ts" server="headless.worldsecuresystems.com" local="130079159120000000" remote="130079159120000000" Dst="0" />
<file name="fileSequence19.ts" server="headless.worldsecuresystems.com" local="130079159170000000" remote="130079159170000000" Dst="0" />
<file name="fileSequence2.ts" server="headless.worldsecuresystems.com" local="130079159210000000" remote="130079159210000000" Dst="0" />
<file name="fileSequence20.ts" server="headless.worldsecuresystems.com" local="130079159250000000" remote="130079159250000000" Dst="0" />
<file name="fileSequence21.ts" server="headless.worldsecuresystems.com" local="130079159270000000" remote="130079159270000000" Dst="0" />
<file name="fileSequence22.ts" server="headless.worldsecuresystems.com" local="130079159320000000" remote="130079159320000000" Dst="0" />
<file name="fileSequence23.ts" server="headless.worldsecuresystems.com" local="130079159370000000" remote="130079159370000000" Dst="0" />
<file name="fileSequence24.ts" server="headless.worldsecuresystems.com" local="130079159410000000" remote="130079159410000000" Dst="0" />
<file name="fileSequence25.ts" server="headless.worldsecuresystems.com" local="130079159470000000" remote="130079159470000000" Dst="0" />
<file name="fileSequence26.ts" server="headless.worldsecuresystems.com" local="130079159510000000" remote="130079159510000000" Dst="0" />
<file name="fileSequence27.ts" server="headless.worldsecuresystems.com" local="130079159550000000" remote="130079159550000000" Dst="0" />
<file name="fileSequence28.ts" server="headless.worldsecuresystems.com" local="130079159590000000" remote="130079159590000000" Dst="0" />
<file name="fileSequence29.ts" server="headless.worldsecuresystems.com" local="130079159630000000" remote="130079159630000000" Dst="0" />
<file name="fileSequence3.ts" server="headless.worldsecuresystems.com" local="130079159670000000" remote="130079159670000000" Dst="0" />
<file name="fileSequence30.ts" server="headless.worldsecuresystems.com" local="130079159710000000" remote="130079159710000000" Dst="0" />
<file name="fileSequence31.ts" server="headless.worldsecuresystems.com" local="130079159750000000" remote="130079159750000000" Dst="0" />
<file name="fileSequence32.ts" server="headless.worldsecuresystems.com" local="130079159780000000" remote="130079159780000000" Dst="0" />
<file name="fileSequence33.ts" server="headless.worldsecuresystems.com" local="130079159830000000" remote="130079159830000000" Dst="0" />
<file name="fileSequence34.ts" server="headless.worldsecuresystems.com" local="130079159870000000" remote="130079159870000000" Dst="0" />
<file name="fileSequence35.ts" server="headless.worldsecuresystems.com" local="130079159930000000" remote="130079159930000000" Dst="0" />
<file name="fileSequence36.ts" server="headless.worldsecuresystems.com" local="130079159970000000" remote="130079159970000000" Dst="0" />
<file name="fileSequence37.ts" server="headless.worldsecuresystems.com" local="130079160020000000" remote="130079160020000000" Dst="0" />
<file name="fileSequence38.ts" server="headless.worldsecuresystems.com" local="130079160050000000" remote="130079160050000000" Dst="0" />
<file name="fileSequence39.ts" server="headless.worldsecuresystems.com" local="130079160060000000" remote="130079160060000000" Dst="0" />
<file name="fileSequence4.ts" server="headless.worldsecuresystems.com" local="130079160110000000" remote="130079160110000000" Dst="0" />
<file name="fileSequence5.ts" server="headless.worldsecuresystems.com" local="130079160150000000" remote="130079160150000000" Dst="0" />
<file name="fileSequence6.ts" server="headless.worldsecuresystems.com" local="130079160190000000" remote="130079160190000000" Dst="0" />
<file name="fileSequence7.ts" server="headless.worldsecuresystems.com" local="130079160230000000" remote="130079160230000000" Dst="0" />
<file name="fileSequence8.ts" server="headless.worldsecuresystems.com" local="130079160290000000" remote="130079160290000000" Dst="0" />
<file name="fileSequence9.ts" server="headless.worldsecuresystems.com" local="130079160360000000" remote="130079160360000000" Dst="0" />
<file name="prog_index.m3u8" server="headless.worldsecuresystems.com" local="130079160370000000" remote="130079160370000000" Dst="0" />
<file name="prog_info.plist" server="headless.worldsecuresystems.com" local="130079160380000000" remote="130079160380000000" Dst="0" />
</dwsync>